haystack_integrations/components/generators/py.typed
haystack_integrations/components/generators/cometapi/__init__.py
haystack_integrations/components/generators/cometapi/chat/chat_generator.py
cometapi_haystack-2.0.0.dist-info/METADATA
cometapi_haystack-2.0.0.dist-info/WHEEL
cometapi_haystack-2.0.0.dist-info/licenses/LICENSE.txt
cometapi_haystack-2.0.0.dist-info/RECORD
