Metadata-Version: 2.4
Name: cometapi-haystack
Version: 2.0.0
Summary: Use Comet API with Haystack to build AI applications with 500+ AI models.
Project-URL: Documentation, https://github.com/deepset-ai/haystack-core-integrations/tree/main/integrations/cometapi#readme
Project-URL: Issues, https://github.com/deepset-ai/haystack-core-integrations/issues
Project-URL: Source, https://github.com/deepset-ai/haystack-core-integrations/tree/main/integrations/cometapi
Author-email: deepset GmbH <info@deepset.ai>, Gary Badwal <gurpreet071999@gmail.com>
License-Expression: Apache-2.0
License-File: LICENSE.txt
Classifier: Development Status :: 4 - Beta
Classifier: License :: OSI Approved :: Apache Software License
Classifier: Programming Language :: Python
Classifier: Programming Language :: Python :: 3.10
Classifier: Programming Language :: Python :: 3.11
Classifier: Programming Language :: Python :: 3.12
Classifier: Programming Language :: Python :: 3.13
Classifier: Programming Language :: Python :: Implementation :: CPython
Classifier: Programming Language :: Python :: Implementation :: PyPy
Requires-Python: >=3.10
Requires-Dist: haystack-ai>=2.22.0
